numstore.py
numstore-1.2.6.data/scripts/numstore.py
numstore-1.2.6.dist-info/LICENSE
numstore-1.2.6.dist-info/METADATA
numstore-1.2.6.dist-info/WHEEL
numstore-1.2.6.dist-info/top_level.txt
numstore-1.2.6.dist-info/RECORD
