Metadata-Version: 2.1
Name: numstore
Version: 1.2.6
Summary: numstore - fast and easy key-value storage in RAM. It only works with numbers keys and numbers values
Home-page: https://github.com/anydict/numstore
Author: anydict
Author-email: novi4kom@gmail.com
License: MIT
Keywords: fast easy key value storage RAM memory only for number
Classifier: Intended Audience :: Developers
Classifier: License :: OSI Approved :: MIT License
Classifier: Operating System :: OS Independent
Classifier: Programming Language :: Python :: 3
Classifier: Topic :: Database
Requires-Python: >=3.10
License-File: LICENSE
